nexroo_cli/__init__.py
nexroo_cli/addon_loader.py
nexroo_cli/config.py
nexroo_cli/installer.py
nexroo_cli/main.py
nexroo_cli/package_manager.py
nexroo_cli/workflow_manager.py
nexroo_cli/auth/__init__.py
nexroo_cli/auth/config.py
nexroo_cli/auth/jwt_verifier.py
nexroo_cli/auth/manager.py
nexroo_cli/auth/oidc_client.py
nexroo_cli/auth/token_storage.py
nexroo_cli-1.7.1.dist-info/licenses/LICENSE
nexroo_cli-1.7.1.dist-info/METADATA
nexroo_cli-1.7.1.dist-info/WHEEL
nexroo_cli-1.7.1.dist-info/entry_points.txt
nexroo_cli-1.7.1.dist-info/top_level.txt
nexroo_cli-1.7.1.dist-info/RECORD
