Metadata-Version: 2.4
Name: nexroo-cli
Version: 1.7.1
Summary: CLI wrapper for ai-rooms-script with Zitadel authentication
Author-email: Synvex <contact@synvex.ai>
License: Nexroo Engine Free Use License v1.0
Project-URL: Homepage, https://github.com/nexroo-ai/nexroo-cli
Project-URL: Repository, https://github.com/nexroo-ai/nexroo-cli
Classifier: Development Status :: 3 - Alpha
Classifier: Intended Audience :: Developers
Classifier: License :: Other/Proprietary License
Classifier: Programming Language :: Python :: 3
Classifier: Programming Language :: Python :: 3.10
Classifier: Programming Language :: Python :: 3.11
Classifier: Programming Language :: Python :: 3.12
Classifier: Programming Language :: Python :: 3.13
Requires-Python: <3.14,>=3.10
License-File: LICENSE
Requires-Dist: loguru>=0.7.0
Requires-Dist: httpx>=0.28.1
Requires-Dist: cryptography>=43.0.0
Requires-Dist: python-jose[cryptography]>=3.3.0
Requires-Dist: aiohttp>=3.9.0
Dynamic: license-file
